loki_urllib3_client.py
loki_urllib3_client-0.2.2.dist-info/METADATA
loki_urllib3_client-0.2.2.dist-info/WHEEL
loki_urllib3_client-0.2.2.dist-info/licenses/LICENSE
loki_urllib3_client-0.2.2.dist-info/RECORD
