Metadata-Version: 2.3
Name: loki-urllib3-client
Version: 0.2.2
Summary: A simple loki client using urllib3
Author-email: Jimmy Christensen <lithorus@gmail.com>
Classifier: License :: OSI Approved :: MIT License
Classifier: Operating System :: OS Independent
Classifier: Programming Language :: Python :: 3
Requires-Python: >3.7
Requires-Dist: urllib3
